legend_pygeom_tools-0.2.0.dist-info/licenses/LICENSE
pygeomtools/__init__.py
pygeomtools/_version.py
pygeomtools/detectors.py
pygeomtools/geometry.py
pygeomtools/utils.py
pygeomtools/viewer.py
pygeomtools/viewer_scene_schema.yaml
pygeomtools/visualization.py
pygeomtools/write.py
pygeomtools/materials/__init__.py
pygeomtools/materials/base.py
pygeomtools/materials/legend.py
legend_pygeom_tools-0.2.0.dist-info/METADATA
legend_pygeom_tools-0.2.0.dist-info/WHEEL
legend_pygeom_tools-0.2.0.dist-info/entry_points.txt
legend_pygeom_tools-0.2.0.dist-info/top_level.txt
legend_pygeom_tools-0.2.0.dist-info/RECORD
