Metadata-Version: 2.4
Name: legend_pygeom_tools
Version: 0.2.0
Summary: Python tools to handle Monte Carlo simulation geometry
Author-email: Luigi Pertoldi <gipert@pm.me>
Maintainer: The LEGEND Collaboration
License-Expression: GPL-3.0
Project-URL: Homepage, https://github.com/legend-exp/legend-pygeom-tools
Project-URL: Bug Tracker, https://github.com/legend-exp/legend-pygeom-tools/issues
Project-URL: Discussions, https://github.com/legend-exp/legend-pygeom-tools/discussions
Project-URL: Changelog, https://github.com/legend-exp/legend-pygeom-tools/releases
Classifier: Intended Audience :: Developers
Classifier: Intended Audience :: Science/Research
Classifier: Operating System :: MacOS
Classifier: Operating System :: POSIX
Classifier: Operating System :: Unix
Classifier: Programming Language :: Python
Classifier: Programming Language :: Python :: 3
Classifier: Programming Language :: Python :: 3 :: Only
Classifier: Topic :: Scientific/Engineering
Requires-Python: >=3.10
License-File: LICENSE
Requires-Dist: numpy
Requires-Dist: pyg4ometry
Requires-Dist: dbetto
Requires-Dist: legend-pydataobj>=0.15.0
Requires-Dist: legend-pygeom-optics>=0.15
Requires-Dist: pint
Requires-Dist: jsonschema
Provides-Extra: all
Requires-Dist: legend-pygeom-tools[docs,test]; extra == "all"
Provides-Extra: docs
Requires-Dist: furo; extra == "docs"
Requires-Dist: myst-parser; extra == "docs"
Requires-Dist: sphinx; extra == "docs"
Requires-Dist: sphinx-copybutton; extra == "docs"
Provides-Extra: test
Requires-Dist: pre-commit; extra == "test"
Requires-Dist: pylegendtestdata; extra == "test"
Requires-Dist: pytest>=6.0; extra == "test"
Requires-Dist: pytest-cov; extra == "test"
Dynamic: license-file
